{
    "live_channels": [
        {
            "streamer_name": "Jake",
            "streamer_avatar": "https://picsum.photos/id/1013/534/300",
            "stream_title": "I don't know",
            "category_name": "Just Chatting",
            "tag": "English",
            "thumbnail": "https://picsum.photos/id/1022/534/300",
            "views": "4.2K"
        },
        {
            "streamer_name": "Tommy",
            "streamer_avatar": "https://picsum.photos/id/1012/534/300",
            "stream_title": "Friday stream",
            "category_name": "StarCraft",
            "tag": "Strategy",
            "thumbnail": "https://picsum.photos/id/1021/534/300",
            "views": "513"
        }
    ],
    "recommended_channels": [
        {
            "streamer_name": "King",
            "streamer_avatar": "https://picsum.photos/id/1001/534/300",
            "stream_title": "Kappa",
            "category_name": "World of Warcraft",
            "tag": "MMORPG",
            "thumbnail": "https://picsum.photos/id/1039/534/300",
            "views": "5.6K"
        },
        {
            "streamer_name": "Erik",
            "streamer_avatar": "https://picsum.photos/id/1002/534/300",
            "stream_title": "Yo",
            "category_name": "StarCraft",
            "tag": "Strategy",
            "thumbnail": "https://picsum.photos/id/1033/534/300",
            "views": "513"
        },
        {
            "streamer_name": "Lily",
            "streamer_avatar": "https://picsum.photos/id/1003/534/300",
            "stream_title": "Chill Stream",
            "category_name": "League of Legends",
            "tag": "Competitive",
            "thumbnail": "https://picsum.photos/id/1022/534/300",
            "views": "10.1K"
        },
        {
            "streamer_name": "Molly",
            "streamer_avatar": "https://picsum.photos/id/1004/534/300",
            "stream_title": "Hey guys",
            "category_name": "Music",
            "tag": "English",
            "thumbnail": "https://picsum.photos/id/1032/534/300",
            "views": "69"
        }
    ],
    "offline_channels": [
        {
            "streamer_name": "Emily",
            "streamer_avatar": "https://picsum.photos/id/1024/100/100",
            "new_videos": "2"
        },
        {
            "streamer_name": "James",
            "streamer_avatar": "https://picsum.photos/id/1074/100/100",
            "new_videos": "3"
        },
        {
            "streamer_name": "HotDog",
            "streamer_avatar": "https://picsum.photos/id/152/100/100",
            "new_videos": "0"
        }
    ]
}